bowser/__init__.py
bowser/bowser tests.py
bowser/browser.py
bowser-0.2.2.dist-info/LICENSE
bowser-0.2.2.dist-info/METADATA
bowser-0.2.2.dist-info/WHEEL
bowser-0.2.2.dist-info/top_level.txt
bowser-0.2.2.dist-info/RECORD
