Metadata-Version: 2.1
Name: bowser
Version: 0.2.2
Summary: A powerful and intuitive web automation toolkit built on Selenium.
Author-email: Chase Reed <chasereed00000@gmail.com>
License: MIT License
Keywords: automation,selenium,web,browser,stealth
Classifier: Programming Language :: Python :: 3
Classifier: License :: OSI Approved :: MIT License
Classifier: Operating System :: OS Independent
Requires-Python: >=3.7
License-File: LICENSE
Requires-Dist: selenium>=4.0.0
Requires-Dist: webdriver-manager
Requires-Dist: fake-useragent
